MANIFEST.in
README.md
setup.py
alphafold2mmopt/__init__.py
alphafold2mmopt/run.py
alphafold2mmopt/utils.py
alphafold2mmopt.egg-info/PKG-INFO
alphafold2mmopt.egg-info/SOURCES.txt
alphafold2mmopt.egg-info/dependency_links.txt
alphafold2mmopt.egg-info/entry_points.txt
alphafold2mmopt.egg-info/requires.txt
alphafold2mmopt.egg-info/top_level.txt
alphafold2mmopt/common/__init__.py
alphafold2mmopt/common/cleanup.py
alphafold2mmopt/common/protein.py
alphafold2mmopt/common/residue_constants.py
alphafold2mmopt/relax/__init__.py
alphafold2mmopt/relax/localminimizer.py
alphafold2mmopt/relax/utils.py